[
    {
        "name": "A Little Party Never Killed Nobody (All We Got)",
        "artist": "Fergie Ft. Q-Tip, GoonRock",
        "coaches": "Solo",
        "difficulty": "Easy",
        "origin": "Just Dance 2019",
        "catalog": "Unlimited",
        "theme": "",
        "ref": "https://vignette.wikia.nocookie.net/justdance/images/d/dc/Littleparty_cover_generic.png/revision/latest/scale-to-width-down/180?cb=20181022221316"
    },
    {
        "name": "A Little Party Never Killed Nobody (All We Got)",
        "artist": "Fergie Ft. Q-Tip, GoonRock",
        "coaches": "Trio",
        "difficulty": "Hard",
        "origin": "Just Dance 2019",
        "catalog": "Unlimited",
        "theme": "Roarin' Twenties",
        "ref": "https://vignette.wikia.nocookie.net/justdance/images/3/3c/Littlepartyalt_cover_generic.png/revision/latest/scale-to-width-down/180?cb=20181022215638"
    },
    {
        "name": "A Pirate You Shall Be",
        "artist": "Tom Zehnder",
        "coaches": "Solo",
        "difficulty": "Medium",
        "origin": "Just Dance Kids",
        "catalog": "Unlimited",
        "theme": "",
        "ref": "https://vignette.wikia.nocookie.net/justdance/images/3/35/KIDSPirateYouShallBe_Cover_Generic.tga.png/revision/latest/scale-to-width-down/180?cb=20161124185650"
    },
    {
        "name": "Acceptable In The 80s",
        "artist": "Calvin Harris",
        "coaches": "Solo",
        "difficulty": "Easy",
        "origin": "Just Dance 1",
        "catalog": "Unlimited",
        "theme": "",
        "ref": "https://vignette.wikia.nocookie.net/justdance/images/e/ef/Acceptable.jpg/revision/latest/scale-to-width-down/180?cb=20150410141322"
    },
    {
        "name": "Accidentally in Love",
        "artist": "Counting Crows",
        "coaches": "Solo",
        "difficulty": "Medium",
        "origin": "Just Dance Kids",
        "catalog": "Unlimited",
        "theme": "",
        "ref": "https://vignette.wikia.nocookie.net/justdance/images/3/36/KIDSAccidentallyInLove_cover_generic.jpg/revision/latest/scale-to-width-down/180?cb=20180419093049"
    },
    {
        "name": "Adeyyo",
        "artist": "Ece Seçkin",
        "coaches": "Solo",
        "difficulty": "Easy",
        "origin": "Just Dance 2019",
        "catalog": "Unlimited",
        "theme": "",
        "ref": "https://vignette.wikia.nocookie.net/justdance/images/a/af/Adeyyo_cover_generic.png/revision/latest/scale-to-width-down/180?cb=20181023044136"
    },
    {
        "name": "Ain't My Fault",
        "artist": "Zara Larsson",
        "coaches": "Solo",
        "difficulty": "Medium",
        "origin": "Just Dance 2017",
        "catalog": "Unlimited",
        "theme": "",
        "ref": "https://vignette.wikia.nocookie.net/justdance/images/4/44/AintMy_Cover_Generic.png/revision/latest/scale-to-width-down/180?cb=20170530100033"
    },
    {
        "name": "Airplanes",
        "artist": "B.o.B Ft. Hayley Williams of Paramore",
        "coaches": "Solo",
        "difficulty": "Easy",
        "origin": "Just Dance 3",
        "catalog": "Unlimited",
        "theme": "",
        "ref": "https://vignette.wikia.nocookie.net/justdance/images/8/86/Airplanes_jdnow.jpg/revision/latest/scale-to-width-down/180?cb=20150412231845"
    },
    {
        "name": "All About That Bass",
        "artist": "Meghan Trainor",
        "coaches": "Solo",
        "difficulty": "Medium",
        "origin": "Just Dance 2016",
        "catalog": "Unlimited",
        "theme": "",
        "ref": "https://vignette.wikia.nocookie.net/justdance/images/4/40/Aboutthatbass_cover_generic.png/revision/latest/scale-to-width-down/180?cb=20170208081852"
    },
    {
        "name": "All About That Bass",
        "artist": "Meghan Trainor",
        "coaches": "Duet",
        "difficulty": "Medium",
        "origin": "Just Dance 2016",
        "catalog": "Unlimited",
        "theme": "Flower & Bee",
        "ref": "https://vignette.wikia.nocookie.net/justdance/images/1/16/Aboutthatbassalt_cover_generic.png/revision/latest/scale-to-width-down/180?cb=20170208084206"
    },
    {
        "name": "All About Us",
        "artist": "Jordan Fisher",
        "coaches": "Trio",
        "difficulty": "Medium",
        "origin": "Just Dance 2017",
        "catalog": "Unlimited",
        "theme": "",
        "ref": "https://vignette.wikia.nocookie.net/justdance/images/5/51/Allaboutus.png/revision/latest/scale-to-width-down/180?cb=20161028111002"
    },
    {
        "name": "All You Gotta Do",
        "artist": "The Just Dance Band",
        "coaches": "Solo",
        "difficulty": "Easy",
        "origin": "Just Dance 2018",
        "catalog": "Unlimited",
        "theme": "",
        "ref": "https://vignette.wikia.nocookie.net/justdance/images/d/df/Allyougotta_cover_generic_8thgen.jpg/revision/latest?cb=20171015184937"
    },
    {
        "name": "Alphabet Song",
        "artist": "The Just Dance Kids",
        "coaches": "Solo",
        "difficulty": "Medium",
        "origin": "Just Dance Kids",
        "catalog": "Unlimited",
        "theme": "",
        "ref": "https://vignette.wikia.nocookie.net/justdance/images/8/80/Kidsabc.jpg/revision/latest/scale-to-width-down/180?cb=20161201112335"
    },
    {
        "name": "Always Look On The Bright Side Of Life",
        "artist": "The Frankie Bostello Orchestra",
        "coaches": "Quartet",
        "difficulty": "Easy",
        "origin": "Just Dance 2020",
        "catalog": "",
        "theme": "",
        "ref": ""
    },
    {
        "name": "Am I Wrong",
        "artist": "Nico & Vinz",
        "coaches": "Solo",
        "difficulty": "Medium",
        "origin": "Just Dance 2016",
        "catalog": "Unlimited",
        "theme": "",
        "ref": "https://vignette.wikia.nocookie.net/justdance/images/a/a3/AmIWrong.png/revision/latest/scale-to-width-down/180?cb=20170208081918"
    },
    {
        "name": "American Girl",
        "artist": "Bonnie McKee",
        "coaches": "Solo",
        "difficulty": "Medium",
        "origin": "Just Dance 2014",
        "catalog": "Unlimited",
        "theme": "",
        "ref": "https://vignette.wikia.nocookie.net/justdance/images/1/1c/Americangirldlc_cover_generic.jpg/revision/latest/scale-to-width-down/180?cb=20140928054638"
    },
    {
        "name": "Animals",
        "artist": "Martin Garrix",
        "coaches": "Duet",
        "difficulty": "Hard",
        "origin": "Just Dance 2014",
        "catalog": "Unlimited",
        "theme": "",
        "ref": "https://vignette.wikia.nocookie.net/justdance/images/d/d5/AnimalsSqu.png/revision/latest/scale-to-width-down/180?cb=20170208081958"
    },
    {
        "name": "Animals",
        "artist": "Martin Garrix",
        "coaches": "Solo",
        "difficulty": "Extreme",
        "origin": "Just Dance 2016",
        "catalog": "Unlimited",
        "theme": "Extreme",
        "ref": "https://vignette.wikia.nocookie.net/justdance/images/6/61/AnimalsALT.png/revision/latest/scale-to-width-down/180?cb=20170208084214"
    },
    {
        "name": "Another One Bites The Dust",
        "artist": "Queen",
        "coaches": "Quartet",
        "difficulty": "Easy",
        "origin": "Just Dance 2018",
        "catalog": "Unlimited",
        "theme": "",
        "ref": "https://vignette.wikia.nocookie.net/justdance/images/b/be/Anotherone_cover_generic.jpg/revision/latest/scale-to-width-down/180?cb=20171015184937"
    },
    {
        "name": "Another One Bites The Dust",
        "artist": "Queen",
        "coaches": "Solo",
        "difficulty": "Hard",
        "origin": "Just Dance 2018",
        "catalog": "Unlimited",
        "theme": "Stunt",
        "ref": "https://vignette.wikia.nocookie.net/justdance/images/7/73/Anotheronealt_cover_generic.jpg/revision/latest/scale-to-width-down/180?cb=20171015184938"
    },
    {
        "name": "Apache (Jump On It)",
        "artist": "The Sugarhill Gang",
        "coaches": "Solo",
        "difficulty": "Medium",
        "origin": "Just Dance 3",
        "catalog": "Unlimited",
        "theme": "",
        "ref": "https://vignette.wikia.nocookie.net/justdance/images/7/72/Apachejdn.jpg/revision/latest/scale-to-width-down/180?cb=20150929190308"
    },
    {
        "name": "Applause",
        "artist": "Lady Gaga",
        "coaches": "Solo",
        "difficulty": "Easy",
        "origin": "Just Dance 2014",
        "catalog": "Unlimited",
        "theme": "",
        "ref": "https://vignette.wikia.nocookie.net/justdance/images/9/90/Limagolf1_cover_generic.png/revision/latest/scale-to-width-down/180?cb=20171107151350"
    },
    {
        "name": "Aquarius/Let The Sunshine In",
        "artist": "The Sunlight Shakers",
        "coaches": "Duet",
        "difficulty": "Easy",
        "origin": "Just Dance 2014",
        "catalog": "Unlimited",
        "theme": "",
        "ref": "https://vignette.wikia.nocookie.net/justdance/images/6/64/Aquarius_cover_generic.png/revision/latest/scale-to-width-down/180?cb=20171107151237"
    },
    {
        "name": "Aserejé (The Ketchup Song)",
        "artist": "Las Ketchup",
        "coaches": "Duet",
        "difficulty": "Easy",
        "origin": "Just Dance 4",
        "catalog": "Unlimited",
        "theme": "",
        "ref": "https://vignette.wikia.nocookie.net/justdance/images/f/f1/Ketchupsong.jpg/revision/latest/scale-to-width-down/180?cb=20140928224051"
    },
    {
        "name": "Automaton",
        "artist": "Jamiroquai",
        "coaches": "Solo",
        "difficulty": "Medium",
        "origin": "Just Dance 2018",
        "catalog": "Unlimited",
        "theme": "",
        "ref": "https://vignette.wikia.nocookie.net/justdance/images/d/d6/Automaton_cover_generic.jpg/revision/latest/scale-to-width-down/180?cb=20171015184938"
    },
    {
        "name": "Automaton",
        "artist": "Jamiroquai",
        "coaches": "Solo",
        "difficulty": "Medium",
        "origin": "Just Dance 2018",
        "catalog": "Unlimited",
        "theme": "Tomato",
        "ref": "https://vignette.wikia.nocookie.net/justdance/images/d/de/Automatonalt_cover_generic.jpg/revision/latest/scale-to-width-down/180?cb=20171015184939"
    }
]